start_end_logging/__init__.py
start_end_logging/start_end_logging.py
start_end_logging-0.1.7.dist-info/METADATA
start_end_logging-0.1.7.dist-info/WHEEL
start_end_logging-0.1.7.dist-info/RECORD
