Metadata-Version: 2.1
Name: start-end-logging
Version: 0.1.7
Summary: A very simple logging library that logs the start and end of a process step and, in particular, indicates the elapsed time.
Author: Johannes Lieberherr
Author-email: johannes.lieberherr@ttools.ch
Requires-Python: >=3.8
Classifier: Programming Language :: Python :: 3
Classifier: Programming Language :: Python :: 3.8
Classifier: Programming Language :: Python :: 3.9
Classifier: Programming Language :: Python :: 3.10
Classifier: Programming Language :: Python :: 3.11
Classifier: Programming Language :: Python :: 3.12
Project-URL: GitHub Repository, https://github.com/jlieberherr/start-end-logging
